krispy/__init__.py
krispy/graph.py
krispy/matrix.py
krispy/scores.py
krispy/sensitivity.py
krispy-1.0.4.dist-info/METADATA
krispy-1.0.4.dist-info/WHEEL
krispy-1.0.4.dist-info/top_level.txt
krispy-1.0.4.dist-info/RECORD
