Metadata-Version: 2.1
Name: krispy
Version: 1.0.4
Summary: ahp trade study tools
Home-page: https://github.com/kgearhar/krispy
Author: Kristen Gearhart
Author-email: kgears502@gmail.com
License: UNKNOWN
Platform: UNKNOWN
Classifier: Programming Language :: Python :: 3
Classifier: Operating System :: OS Independent
Requires-Python: >=3.8
Requires-Dist: numpy (>=1.19.0)
Requires-Dist: matplotlib (>=3.2.2)
